hfscanstat/__init__.py
hfscanstat/_nbdev.py
hfscanstat/scanstat.py
hfscanstat-0.0.1.dist-info/LICENSE
hfscanstat-0.0.1.dist-info/METADATA
hfscanstat-0.0.1.dist-info/WHEEL
hfscanstat-0.0.1.dist-info/entry_points.txt
hfscanstat-0.0.1.dist-info/top_level.txt
hfscanstat-0.0.1.dist-info/RECORD
