Metadata-Version: 2.1
Name: hfscanstat
Version: 0.0.1
Summary: A Python implementation of the hypothesis-free scan statistic
Home-page: https://github.com/jazon33y/hfscanstat
Author: Jason O'Rawe
Author-email: jazon33y@gmail.com
License: Apache Software License 2.0
Keywords: scan statistics point-process
Platform: UNKNOWN
Classifier: Development Status :: 3 - Alpha
Classifier: Intended Audience :: Developers
Classifier: License :: OSI Approved :: Apache Software License
Classifier: Natural Language :: English
Classifier: Programming Language :: Python :: 3.6
Classifier: Programming Language :: Python :: 3.7
Classifier: Programming Language :: Python :: 3.8
Requires-Python: >=3.6
Requires-Dist: scipy (==1.3.1)
Requires-Dist: numpy (==1.17.4)
Requires-Dist: pandas (==0.25.3)
